{
  "description": "项目配置文件",
  "setting": {
    "urlCheck": false,
    "es6": true,
    "enhance": true,
    "postcss": true,
    "preloadBackgroundData": false,
    "minified": true,
    "newFeature": false,
    "coverView": true,
    "nodeModules": false,
    "autoAudits": false,
    "showShadowRootInWxmlPanel": true,
    "scopeDataCheck": false,
    "uglifyFileName": false,
    "checkInvalidKey": true,
    "checkSiteMap": true,
    "uploadWithSourceMap": true,
    "compileHotReLoad": false,
    "lazyloadPlaceholderEnable": false,
    "useMultiFrameRuntime": true,
    "babelSetting": {
      "ignore": [],
      "disablePlugins": [],
      "outputPath": ""
    },
    "enableEngineNative": false,
    "useIsolateContext": true,
    "userConfirmedBundleSwitch": false,
    "packNpmManually": true,
    "packNpmRelationList": [
      {
        "packageJsonPath": "package.json",
        "miniprogramNpmDistDir": "miniprogram_npm"
      }
    ],
    "minifyWXSS": true,
    "showES6CompileOption": false,
    "ignoreUploadUnusedFiles": true,
    "useCompilerPlugins": [
      "less"
    ],
    "compileWorklet": false,
    "minifyWXML": true,
    "localPlugins": false,
    "disableUseStrict": false,
    "condition": false,
    "swc": false,
    "disableSWC": true
  },
  "compileType": "miniprogram",
  "condition": {},
  "editorSetting": {
    "tabIndent": "insertSpaces",
    "tabSize": 2
  },
  "packOptions": {
    "ignore": [],
    "include": []
  },
  "appid": "wxc5c6eef50aa07409",
  "libVersion": "3.8.2",
  "simulatorPluginLibVersion": {}
}
